pillowcases/__init__.py
pillowcases/pillowcases.py
pillowcases-0.1.0.dist-info/LICENSE
pillowcases-0.1.0.dist-info/METADATA
pillowcases-0.1.0.dist-info/WHEEL
pillowcases-0.1.0.dist-info/top_level.txt
pillowcases-0.1.0.dist-info/RECORD
