Metadata-Version: 2.1
Name: pillowcases
Version: 0.1.0
Summary: Library that makes it possible to work in a concise, algebraic way with Python Imaging Library image objects.
Author: Andrei Lapets
Author-email: a@lapets.io
License: MIT
Project-URL: Repository, https://github.com/lapets/pillowcases
Project-URL: Documentation, https://pillowcases.readthedocs.io
Requires-Python: >=3.7
License-File: LICENSE
Requires-Dist: pillow ~=9.5
Provides-Extra: coveralls
Requires-Dist: coveralls ~=3.3.1 ; extra == 'coveralls'
Provides-Extra: docs
Requires-Dist: toml ~=0.10.2 ; extra == 'docs'
Requires-Dist: sphinx ~=4.2.0 ; extra == 'docs'
Requires-Dist: sphinx-rtd-theme ~=1.0.0 ; extra == 'docs'
Provides-Extra: lint
Requires-Dist: pylint ~=2.17.0 ; extra == 'lint'
Provides-Extra: publish
Requires-Dist: build ~=0.10 ; extra == 'publish'
Requires-Dist: twine ~=4.0 ; extra == 'publish'
Provides-Extra: test
Requires-Dist: pytest ~=7.2 ; extra == 'test'
Requires-Dist: pytest-cov ~=4.0 ; extra == 'test'
